conf/__init__.py
conf/oneCloudTagsCheck.py
conf/settings.py
terraform_resource_tag_check-2.0.0.dist-info/METADATA
terraform_resource_tag_check-2.0.0.dist-info/WHEEL
terraform_resource_tag_check-2.0.0.dist-info/top_level.txt
terraform_resource_tag_check-2.0.0.dist-info/RECORD
